{"kind":"command_create_response","stale_commands":[{"kind":"command","results":[{"type":"label","id":5321,"project_id":98,"name":"plans","created_at":1469016000000,"updated_at":1469016000000,"counts":{"number_of_zero_point_stories_by_state":{"accepted":0,"started":0,"finished":0,"unstarted":0,"planned":0,"delivered":0,"unscheduled":0,"rejected":0,"kind":"counts_by_story_state"},"sum_of_story_estimates_by_state":{"accepted":0,"started":0,"finished":0,"unstarted":0,"planned":0,"delivered":0,"unscheduled":0,"rejected":0,"kind":"counts_by_story_state"},"number_of_stories_by_state":{"accepted":0,"started":0,"finished":0,"unstarted":0,"planned":0,"delivered":0,"unscheduled":0,"rejected":0,"kind":"counts_by_story_state"},"kind":"story_counts"}},{"type":"label","id":5322,"project_id":98,"name":"rebel bases","created_at":1469016000000,"updated_at":1469016000000,"counts":{"number_of_zero_point_stories_by_state":{"accepted":0,"started":0,"finished":0,"unstarted":0,"planned":0,"delivered":0,"unscheduled":0,"rejected":0,"kind":"counts_by_story_state"},"sum_of_story_estimates_by_state":{"accepted":0,"started":0,"finished":0,"unstarted":0,"planned":0,"delivered":0,"unscheduled":0,"rejected":0,"kind":"counts_by_story_state"},"number_of_stories_by_state":{"accepted":0,"started":0,"finished":0,"unstarted":0,"planned":0,"delivered":0,"unscheduled":0,"rejected":0,"kind":"counts_by_story_state"},"kind":"story_counts"}}],"activity":{"kind":"label_create_activity","guid":"98_4","project_version":4,"message":"Darth Vader created labels: \"plans\", \"rebel bases\"","highlight":"created","changes":[{"kind":"label","change_type":"create","id":5321,"new_values":{"id":5321,"project_id":98,"name":"plans","created_at":"2016-07-20T12:00:00Z","updated_at":"2016-07-20T12:00:00Z","counts":{"number_of_zero_point_stories_by_state":{"accepted":0,"started":0,"finished":0,"unstarted":0,"planned":0,"delivered":0,"unscheduled":0,"rejected":0,"kind":"counts_by_story_state"},"sum_of_story_estimates_by_state":{"accepted":0,"started":0,"finished":0,"unstarted":0,"planned":0,"delivered":0,"unscheduled":0,"rejected":0,"kind":"counts_by_story_state"},"number_of_stories_by_state":{"accepted":0,"started":0,"finished":0,"unstarted":0,"planned":0,"delivered":0,"unscheduled":0,"rejected":0,"kind":"counts_by_story_state"},"kind":"story_counts"}},"name":"plans"},{"kind":"label","change_type":"create","id":5322,"new_values":{"id":5322,"project_id":98,"name":"rebel bases","created_at":"2016-07-20T12:00:00Z","updated_at":"2016-07-20T12:00:00Z","counts":{"number_of_zero_point_stories_by_state":{"accepted":0,"started":0,"finished":0,"unstarted":0,"planned":0,"delivered":0,"unscheduled":0,"rejected":0,"kind":"counts_by_story_state"},"sum_of_story_estimates_by_state":{"accepted":0,"started":0,"finished":0,"unstarted":0,"planned":0,"delivered":0,"unscheduled":0,"rejected":0,"kind":"counts_by_story_state"},"number_of_stories_by_state":{"accepted":0,"started":0,"finished":0,"unstarted":0,"planned":0,"delivered":0,"unscheduled":0,"rejected":0,"kind":"counts_by_story_state"},"kind":"story_counts"}},"name":"rebel bases"}],"primary_resources":[{"kind":"label","id":5321,"name":"plans"},{"kind":"label","id":5322,"name":"rebel bases"}],"project":{"kind":"project","id":98,"name":"Learn About the Force"},"performed_by":{"kind":"person","id":101,"name":"Darth Vader","initials":"DV"},"occurred_at":"2016-07-20T12:00:00Z"},"mutandum":[],"parameters":{"labels":[{"name":"plans"},{"name":"rebel bases"}]},"person_id":101,"type":"multi_label_create","project":{"id":98,"version":4}}],"result":"stale"}